pylint_actions/__init__.py
pylint_actions-0.6.0.dist-info/METADATA
pylint_actions-0.6.0.dist-info/WHEEL
pylint_actions-0.6.0.dist-info/licenses/LICENSE
pylint_actions-0.6.0.dist-info/RECORD
