Metadata-Version: 2.4
Name: pylint-actions
Version: 0.6.0
Summary: Pylint plugin for GitHub Actions
Author-email: skhomuti <skhomuti@gmail.com>
License-Expression: MIT
License-File: LICENSE
Keywords: actions,github,linter,pylint,python,static code analysis
Classifier: Development Status :: 4 - Beta
Classifier: Environment :: Console
Classifier: Intended Audience :: Developers
Classifier: License :: OSI Approved :: MIT License
Classifier: Operating System :: OS Independent
Classifier: Programming Language :: Python
Classifier: Programming Language :: Python :: 3
Classifier: Programming Language :: Python :: Implementation :: CPython
Classifier: Programming Language :: Python :: Implementation :: PyPy
Classifier: Topic :: Software Development :: Libraries :: Python Modules
Classifier: Topic :: Software Development :: Quality Assurance
Classifier: Topic :: Software Development :: Testing
Requires-Python: >=3.9
Requires-Dist: pylint<4,>=3.0.3
Provides-Extra: dev
Requires-Dist: pylint<4,>=3.0.3; extra == 'dev'
